[[{"Recommended": "Yes", "CEO Approval": "N/A", "Business Outlook": "N/A", "Work/Life Balance": 4, "Culture & Values": 5, "Diversity and Inclusion": 5, "Career Opportunities": 5, "Compensation and Benefits": 3, "Senior Management": 5, "review_title": "Loved the job!", "rating": "5.0", "reviewer_affiliation": "Former Employee, less than 1 year", "job_date": "22 Mar 2023", "job_title": "Conference Manager in Bloomington, IL", "duration": "N/A", "pros": "I loved my coworkers and the living environment. Great experience to talk about in future job interviews", "cons": "need to be flexible and be ready for odd hours"}, {"Recommended": "N/A", "CEO Approval": "Neutral", "Business Outlook": "Neutral", "Work/Life Balance": 4, "Culture & Values": 4, "Diversity and Inclusion": 4, "Career Opportunities": 4, "Compensation and Benefits": 4, "Senior Management": 4, "review_title": "Small College", "rating": "4.0", "reviewer_affiliation": "Former Employee, more than 3 years", "job_date": "13 May 2023", "job_title": "Head Coach in Bloomington, IL", "duration": "N/A", "pros": "Benefits, Pay, ability to work various hours", "cons": "Small University, rely heavily on athletics for retaining students."}, {"Recommended": "N/A", "CEO Approval": "N/A", "Business Outlook": "N/A", "Work/Life Balance": "N/A", "Culture & Values": "N/A", "Diversity and Inclusion": "N/A", "Career Opportunities": "N/A", "Compensation and Benefits": "N/A", "Senior Management": "N/A", "review_title": "Great place to work", "rating": "5.0", "reviewer_affiliation": "Current Employee", "job_date": "1 Mar 2023", "job_title": "Residant Assistant in Bloomington, IL", "duration": "N/A", "pros": "Great room for growth and learning", "cons": "No cons or negatives at all"}, {"Recommended": "No", "CEO Approval": "Neutral", "Business Outlook": "Bad", "Work/Life Balance": 3, "Culture & Values": 3, "Diversity and Inclusion": 3, "Career Opportunities": 3, "Compensation and Benefits": 3, "Senior Management": 5, "review_title": "Good", "rating": "3.0", "reviewer_affiliation": "Former Employee, less than 1 year", "job_date": "30 Jun 2022", "job_title": "Summer Grounds Crew in Bloomington, IL", "duration": "N/A", "pros": "Nice staff, straight forward, you always know what you are assigned to and no curve balls.", "cons": "Can be stressful working a labor job all day."}, {"Recommended": "No", "CEO Approval": "No", "Business Outlook": "Bad", "Work/Life Balance": 1, "Culture & Values": 1, "Diversity and Inclusion": 3, "Career Opportunities": 1, "Compensation and Benefits": 3, "Senior Management": 1, "review_title": "Difficult place to work", "rating": "1.0", "reviewer_affiliation": "Current Employee, more than 8 years", "job_date": "22 Feb 2022", "job_title": "Grounds/Maintenance Worker in Bloomington, IL", "duration": "N/A", "pros": "Good benifits if can earn them", "cons": "No raises for 10 years and underpaid department jobs bellow other similar duty jobs at other companies in the region."}, {"Recommended": "No", "CEO Approval": "N/A", "Business Outlook": "N/A", "Work/Life Balance": "N/A", "Culture & Values": "N/A", "Diversity and Inclusion": "N/A", "Career Opportunities": "N/A", "Compensation and Benefits": "N/A", "Senior Management": "N/A", "review_title": "Looks great from the outside...", "rating": "2.0", "reviewer_affiliation": "Former Employee, less than 1 year", "job_date": "18 Mar 2022", "job_title": "Program Coordinator in Bloomington, IL", "duration": "N/A", "pros": "High profile local employer\r\nBeautiful campus\r\nNice offices", "cons": "Layers of bureaucracy, terrible manager"}, {"Recommended": "No", "CEO Approval": "No", "Business Outlook": "Bad", "Work/Life Balance": 1, "Culture & Values": 1, "Diversity and Inclusion": 5, "Career Opportunities": 1, "Compensation and Benefits": 3, "Senior Management": 1, "review_title": "Physical plant", "rating": "1.0", "reviewer_affiliation": "Current Employee, more than 8 years", "job_date": "23 Jun 2021", "job_title": "Physical Plant Manager in Bloomington, IL", "duration": "N/A", "pros": "Working w/ students and faculty at a university.", "cons": "No raise or cost of living raise in 10 years still making the new min. Wage at $15 doubt any new hire at this company will ever get a raise and former employee\u2019s will be now making the same as new employee\u2019s? No raises and no advancement. Have to work w/ temp. Employees daily and Full time employees can\u2019t get work done because they can\u2019t employ enough people for the work that needs to be done? Horrible moral and workplace environment. It is ran like a boot camp? No place for military styles in a public sector? Even though they want to claim they are a private business\ud83d\udc4e Sucks!"}, {"Recommended": "No", "CEO Approval": "N/A", "Business Outlook": "N/A", "Work/Life Balance": 1, "Culture & Values": 1, "Diversity and Inclusion": 1, "Career Opportunities": 1, "Compensation and Benefits": 1, "Senior Management": 1, "review_title": "Pay was not competitive", "rating": "2.0", "reviewer_affiliation": "Former Employee, less than 1 year", "job_date": "27 Oct 2021", "job_title": "Program Coordinator in Bloomington, IL", "duration": "N/A", "pros": "Office furnishings were very nice", "cons": "Hostile work environment, toxic manager. Terrible experience."}, {"Recommended": "Yes", "CEO Approval": "Yes", "Business Outlook": "Good", "Work/Life Balance": 4, "Culture & Values": 4, "Diversity and Inclusion": 3, "Career Opportunities": 4, "Compensation and Benefits": 3, "Senior Management": 4, "review_title": "Baseline Pay", "rating": "4.0", "reviewer_affiliation": "Current Employee, more than 8 years", "job_date": "19 Aug 2021", "job_title": "Associate Director of Development in Bloomington, IL", "duration": "N/A", "pros": "Community is like a family and low turn over of employees.", "cons": "Salary is lower than comparable positions and other universities, of the same size."}, {"Recommended": "Yes", "CEO Approval": "No", "Business Outlook": "Good", "Work/Life Balance": 3, "Culture & Values": 5, "Diversity and Inclusion": 3, "Career Opportunities": 4, "Compensation and Benefits": 3, "Senior Management": 5, "review_title": "Good experience, friendly people", "rating": "4.0", "reviewer_affiliation": "Former Employee, less than 1 year", "job_date": "18 Aug 2021", "job_title": "Adjunct Instructor in Bloomington, IL", "duration": "N/A", "pros": "Small, private university with advanced and highly motivated students. Small class sizes.", "cons": "Very little pay and not a lot of opportunities for advancement"}], [{"Recommended": "N/A", "CEO Approval": "N/A", "Business Outlook": "N/A", "Work/Life Balance": 5, "Culture & Values": 5, "Diversity and Inclusion": 5, "Career Opportunities": 3, "Compensation and Benefits": 4, "Senior Management": 5, "review_title": "Good place to work", "rating": "5.0", "reviewer_affiliation": "Former Employee, more than 1 year", "job_date": "13 Aug 2021", "job_title": "Visiting Assistant Professor in Bloomington, IL", "duration": "N/A", "pros": "Health insurance, friendly working environment", "cons": "I enjoyed my experience as a visiting assistant professor"}, {"Recommended": "Yes", "CEO Approval": "Neutral", "Business Outlook": "Neutral", "Work/Life Balance": 5, "Culture & Values": 5, "Diversity and Inclusion": 3, "Career Opportunities": 4, "Compensation and Benefits": 1, "Senior Management": 3, "review_title": "I was just a student here", "rating": "5.0", "reviewer_affiliation": "Current Employee", "job_date": "2 Jun 2021", "job_title": "Recent College Graduate in Chicago, IL", "duration": "N/A", "pros": "great liberal arts education, small campus environment", "cons": "limited major availability, when it came to education paths."}, {"Recommended": "N/A", "CEO Approval": "N/A", "Business Outlook": "N/A", "Work/Life Balance": "N/A", "Culture & Values": "N/A", "Diversity and Inclusion": "N/A", "Career Opportunities": 5, "Compensation and Benefits": "N/A", "Senior Management": "N/A", "review_title": "Campus Safety", "rating": "5.0", "reviewer_affiliation": "Former Employee", "job_date": "2 Jun 2021", "job_title": "Anonymous Employee in Chicago, IL", "duration": "N/A", "pros": "Great atmosphere and easy to communicate with others.", "cons": "I wouldn't say there were many cons to the job."}, {"Recommended": "Yes", "CEO Approval": "Yes", "Business Outlook": "Good", "Work/Life Balance": 5, "Culture & Values": 5, "Diversity and Inclusion": 3, "Career Opportunities": 5, "Compensation and Benefits": 5, "Senior Management": 5, "review_title": "Fun work place", "rating": "5.0", "reviewer_affiliation": "Current Employee", "job_date": "7 May 2021", "job_title": "Student Ambassador in Bloomington, IL", "duration": "N/A", "pros": "Great office atmosphere\r\nCollaborative team\r\nValued workers", "cons": "There were no cons to working here"}, {"Recommended": "Yes", "CEO Approval": "Neutral", "Business Outlook": "Good", "Work/Life Balance": 4, "Culture & Values": 5, "Diversity and Inclusion": 4, "Career Opportunities": 4, "Compensation and Benefits": 4, "Senior Management": 4, "review_title": "Love it!", "rating": "5.0", "reviewer_affiliation": "Current Employee", "job_date": "17 Apr 2021", "job_title": "Undergraduate Teaching Assistant in Bloomington, IL", "duration": "N/A", "pros": "The biology department is fantastic, understanding and effective.", "cons": "No real cons. Job is fun and interactive."}, {"Recommended": "No", "CEO Approval": "N/A", "Business Outlook": "Neutral", "Work/Life Balance": 3, "Culture & Values": 5, "Diversity and Inclusion": 0, "Career Opportunities": 1, "Compensation and Benefits": 1, "Senior Management": 1, "review_title": "Has great intentions", "rating": "3.0", "reviewer_affiliation": "Current Employee, more than 8 years", "job_date": "23 Feb 2021", "job_title": "Information Technology in Bloomington, IL", "duration": "N/A", "pros": "Great people to work with and very challenging", "cons": "No chance of salary increases and even harder to move up"}, {"Recommended": "N/A", "CEO Approval": "N/A", "Business Outlook": "N/A", "Work/Life Balance": "N/A", "Culture & Values": "N/A", "Diversity and Inclusion": "N/A", "Career Opportunities": "N/A", "Compensation and Benefits": "N/A", "Senior Management": "N/A", "review_title": "Good School, Bad Administration", "rating": "4.0", "reviewer_affiliation": "Current Employee", "job_date": "4 Mar 2021", "job_title": "Anonymous Employee in Bloomington, IL", "duration": "N/A", "pros": "Friendly environment, great students, good working environment", "cons": "old-school administration, focused on money"}, {"Recommended": "N/A", "CEO Approval": "N/A", "Business Outlook": "N/A", "Work/Life Balance": "N/A", "Culture & Values": "N/A", "Diversity and Inclusion": "N/A", "Career Opportunities": "N/A", "Compensation and Benefits": "N/A", "Senior Management": "N/A", "review_title": "IWU", "rating": "5.0", "reviewer_affiliation": "Current Employee", "job_date": "9 Dec 2020", "job_title": "Instructional Staff Member in Bloomington, IL", "duration": "N/A", "pros": "Caring people dedicated to quality education", "cons": "A pandemic makes everything more complicated"}, {"Recommended": "Yes", "CEO Approval": "Yes", "Business Outlook": "Bad", "Work/Life Balance": 5, "Culture & Values": "N/A", "Diversity and Inclusion": "N/A", "Career Opportunities": 3, "Compensation and Benefits": 3, "Senior Management": 3, "review_title": "Good to see if you like Teaching Math", "rating": "4.0", "reviewer_affiliation": "Current Employee, less than 1 year", "job_date": "17 Oct 2014", "job_title": "Math TA in Bloomington, IL", "duration": "N/A", "pros": "Good to see if you like teaching math.\r\nCan be relevant experience if you want to be a teacher or go to graduate school.", "cons": "IWU isn't as selective as it used to be. Some kids will be too lazy in Calc so you'll have to fail them (please don't let them slip by).\r\nThere is always one kid who doesn't know say, FOILing or something.\r\n\r\nAlso IWU doesn't have tons of name recognition when you graduate. Which SUCKS. It makes me wonder if I should've gone to U of I.\r\n\r\nHow bad\\good TAing is varys greatly on the professor you work under and what class you are teaching. An intermediately hard class is best. The HW is super hard to grade, but not everyone takes it."}, {"Recommended": "No", "CEO Approval": "Neutral", "Business Outlook": "Neutral", "Work/Life Balance": 5, "Culture & Values": 4, "Diversity and Inclusion": "N/A", "Career Opportunities": 3, "Compensation and Benefits": 0, "Senior Management": 0, "review_title": "Small team, terrible pay, decent benefits.", "rating": "4.0", "reviewer_affiliation": "Current Employee, more than 3 years", "job_date": "3 Mar 2015", "job_title": "Anonymous Employee in Bloomington, IL", "duration": "N/A", "pros": "Staff receive 20 vacation days a year on top of time off between Christmas and New Years. Unlimited professional development time (if your position has a budget for that). Unlimited sick time, too. It's a pretty small school, so job descriptions are all but worthless; you'll end up working on lots of different things based on your interests.", "cons": "The pay is absolutely terrible, and we haven't gotten a raise in something like eight years, so a lot of our best employees are bailing."}], [{"Recommended": "Yes", "CEO Approval": "Yes", "Business Outlook": "N/A", "Work/Life Balance": "N/A", "Culture & Values": "N/A", "Diversity and Inclusion": "N/A", "Career Opportunities": "N/A", "Compensation and Benefits": "N/A", "Senior Management": "N/A", "review_title": "Ames Library Circulation Desk Student Assistant", "rating": "4.0", "reviewer_affiliation": "Current Employee, more than 1 year", "job_date": "8 Apr 2015", "job_title": "Circulation Desk Assistant, Ames Library in Bloomington, IL", "duration": "N/A", "pros": "Its a great job-mainly shelving books for a bit and siting at the desk checking out/checking in books. Friendly staff and you are even able to do homework when you're not attending to something, which happens more so than not", "cons": "None I can think of. Good place to work i must say. Good place to work I must say. Good place to work I must say. God place to work i must say"}, {"Recommended": "Yes", "CEO Approval": "Yes", "Business Outlook": "Good", "Work/Life Balance": 5, "Culture & Values": "N/A", "Diversity and Inclusion": "N/A", "Career Opportunities": "N/A", "Compensation and Benefits": "N/A", "Senior Management": "N/A", "review_title": "Student with Work Study Position", "rating": "5.0", "reviewer_affiliation": "Former Employee, more than 3 years", "job_date": "19 Mar 2015", "job_title": "Desk Aide in Bloomington, IL", "duration": "N/A", "pros": "I worked as a residential desk aide all four years I was there. Easy application process. I had really nice RCAs and RDs (supervisors) in all the halls I worked in. I was able to get to know so many people who lived in my building or, when I lived and worked in two separate halls, in other halls. Great for my resume.", "cons": "There were some issues when I applied my last year--email response on whether I got the job or not, and where I would be working was slower than usual. Other than that, no other cons."}, {"Recommended": "N/A", "CEO Approval": "N/A", "Business Outlook": "N/A", "Work/Life Balance": 5, "Culture & Values": 5, "Diversity and Inclusion": "N/A", "Career Opportunities": 0, "Compensation and Benefits": 1, "Senior Management": 4, "review_title": "Decent culture and environment, low pay as expected", "rating": "4.0", "reviewer_affiliation": "Current Employee", "job_date": "12 Jul 2015", "job_title": "Teaching Assistant in Bloomington, IL", "duration": "N/A", "pros": "Work as a TA is fairly easy to do and it won't destroy your work life balance.", "cons": "Grading is a pain in the rear, and often times a lot of students only care about grades. Being a TA is a minimum wage job, so don't expect glamour and enough wealth to pay off your student loans, and you won't get a ton of hours either. But that's the sacrifice you make if you're also a student and have other assignments to do."}, {"Recommended": "Yes", "CEO Approval": "Yes", "Business Outlook": "N/A", "Work/Life Balance": 0, "Culture & Values": "N/A", "Diversity and Inclusion": "N/A", "Career Opportunities": 0, "Compensation and Benefits": 4, "Senior Management": 3, "review_title": "It is a great place to work.", "rating": "4.0", "reviewer_affiliation": "Current Employee", "job_date": "4 Jan 2011", "job_title": " in Bloomington, IL", "duration": "N/A", "pros": "The location is great. \r\nThe staff is very nice. \r\nThe benefits are great as well as the time off.\r\nParking and the fitness center is free for faculty and staff.", "cons": "The size of the school, if you want more amenities.\r\nThe students are very needy and the culture caters to all of their wants."}, {"Recommended": "Yes", "CEO Approval": "N/A", "Business Outlook": "Good", "Work/Life Balance": 4, "Culture & Values": 4, "Diversity and Inclusion": "N/A", "Career Opportunities": 3, "Compensation and Benefits": 3, "Senior Management": 5, "review_title": "A great job; good to place to learn more about repairing computers and working with a team", "rating": "5.0", "reviewer_affiliation": "Current Employee, more than 3 years", "job_date": "27 Mar 2013", "job_title": "Desktop Support in Bloomington, IL", "duration": "N/A", "pros": "Get to help people\r\nHave a great boss\r\nLearn new skills\r\nWork with team members and improve team skills\r\nHires both work study and pay roll students", "cons": "Work is based on people reporting issues, so some week have a lot and some have a little\r\nMinimum wage and work study can only work 10 hours a week"}, {"Recommended": "No", "CEO Approval": "Yes", "Business Outlook": "N/A", "Work/Life Balance": 3, "Culture & Values": 4, "Diversity and Inclusion": "N/A", "Career Opportunities": "N/A", "Compensation and Benefits": 0, "Senior Management": 3, "review_title": "Not preparatory for future jobs, but doable as a full-time student.", "rating": "3.0", "reviewer_affiliation": "Former Employee, more than 1 year", "job_date": "5 Jun 2012", "job_title": "Sustainability Educator in Bloomington, IL", "duration": "N/A", "pros": "It's convenient to work on campus as a student. Typically there will be priorities placed on your class schedule.", "cons": "Many times coworkers will not respond to requests for taking shifts, and the blame falls on you. It's difficult to define ones job working for ORL."}, {"Recommended": "Yes", "CEO Approval": "Yes", "Business Outlook": "Good", "Work/Life Balance": "N/A", "Culture & Values": "N/A", "Diversity and Inclusion": "N/A", "Career Opportunities": "N/A", "Compensation and Benefits": "N/A", "Senior Management": "N/A", "review_title": "Work-life balance", "rating": "5.0", "reviewer_affiliation": "Former Employee, more than 5 years", "job_date": "5 Jan 2020", "job_title": "IT Services in Bloomington, IL", "duration": "N/A", "pros": "-it is a close-knit community where everyone knows and helps each other\r\n-encourages work-life balance\r\n-everyone is appreciated on what they do", "cons": "-slow turn-over / upgrade of company technology\r\n-they tend to delay hiring replacements in able to save"}, {"Recommended": "Yes", "CEO Approval": "N/A", "Business Outlook": "Neutral", "Work/Life Balance": 4, "Culture & Values": 5, "Diversity and Inclusion": "N/A", "Career Opportunities": 3, "Compensation and Benefits": 3, "Senior Management": 4, "review_title": "Its a caring, slow paced environment", "rating": "4.0", "reviewer_affiliation": "Former Employee, less than 1 year", "job_date": "3 Jul 2019", "job_title": "Student Worker in Bloomington, IL", "duration": "N/A", "pros": "Coworkers are great. My supervisor and director were very understanding and compassionate. As the title says, this is an academic environment. So, a lot of folks here are interesting and intellectual.", "cons": "There is nothing really."}, {"Recommended": "Yes", "CEO Approval": "Yes", "Business Outlook": "Good", "Work/Life Balance": 4, "Culture & Values": 4, "Diversity and Inclusion": "N/A", "Career Opportunities": 3, "Compensation and Benefits": 0, "Senior Management": 4, "review_title": "French Teaching Assistant", "rating": "4.0", "reviewer_affiliation": "Former Employee, less than 1 year", "job_date": "15 Nov 2016", "job_title": "Assistant Professor in Bloomington, IL", "duration": "N/A", "pros": "Friendly staff and environment. Nice people overall!", "cons": "If you're not used to mid-west weather, you might find it hard to adapt there"}, {"Recommended": "Yes", "CEO Approval": "Yes", "Business Outlook": "Neutral", "Work/Life Balance": 5, "Culture & Values": 3, "Diversity and Inclusion": "N/A", "Career Opportunities": 4, "Compensation and Benefits": 0, "Senior Management": 4, "review_title": "Easy, no work expected", "rating": "3.0", "reviewer_affiliation": "Current Employee, more than 1 year", "job_date": "9 Nov 2013", "job_title": "Desk Aide in Bloomington, IL", "duration": "N/A", "pros": "Working as a DA, you don't even to do mostly anything", "cons": "The pay rate is really low"}], [{"Recommended": "Yes", "CEO Approval": "Yes", "Business Outlook": "Good", "Work/Life Balance": 5, "Culture & Values": 5, "Diversity and Inclusion": "N/A", "Career Opportunities": 4, "Compensation and Benefits": 4, "Senior Management": 5, "review_title": "Good time.", "rating": "5.0", "reviewer_affiliation": "Current Employee, more than 1 year", "job_date": "17 Apr 2014", "job_title": "Multifaith Ambassador in Bloomington, IL", "duration": "N/A", "pros": "Good job.\r\nWonderful employer.\r\nI have no complaints! \r\nGood time.\r\nI enjoyed it.", "cons": "Minimum wage.\r\nLots of events.\r\nYou're with the same 10 people all the time.\r\nInterfaith work."}, {"Recommended": "Yes", "CEO Approval": "N/A", "Business Outlook": "N/A", "Work/Life Balance": 5, "Culture & Values": 5, "Diversity and Inclusion": "N/A", "Career Opportunities": 5, "Compensation and Benefits": 5, "Senior Management": 5, "review_title": "Great Place to Get Experience", "rating": "5.0", "reviewer_affiliation": "Former Employee", "job_date": "27 Sept 2016", "job_title": "Writing Tutor in Bloomington, IL", "duration": "N/A", "pros": "Good culture\r\nGreat experience\r\nFun chance to work with students and professores", "cons": "None at all. Great place to work and get experience!"}, {"Recommended": "N/A", "CEO Approval": "N/A", "Business Outlook": "N/A", "Work/Life Balance": 0, "Culture & Values": "N/A", "Diversity and Inclusion": "N/A", "Career Opportunities": 0, "Compensation and Benefits": 3, "Senior Management": 0, "review_title": "Limited opportunities", "rating": "3.0", "reviewer_affiliation": "Current Employee", "job_date": "24 Feb 2010", "job_title": " in Bloomington, IL", "duration": "N/A", "pros": "Lots of great people to work with.\r\nGood benefits.", "cons": "Low pay.\r\nVery limited opportunities for advancement for staff."}, {"Recommended": "Yes", "CEO Approval": "Yes", "Business Outlook": "Good", "Work/Life Balance": 4, "Culture & Values": 5, "Diversity and Inclusion": 4, "Career Opportunities": 3, "Compensation and Benefits": 3, "Senior Management": 4, "review_title": "Great University", "rating": "4.0", "reviewer_affiliation": "Current Employee", "job_date": "3 Oct 2020", "job_title": "Assistant Director in Bloomington, IL", "duration": "N/A", "pros": "Close knit community and caring employees", "cons": "Very closely tied to alumni community which can sometimes make non alums feel like outsiders"}, {"Recommended": "Yes", "CEO Approval": "Yes", "Business Outlook": "Bad", "Work/Life Balance": 3, "Culture & Values": 5, "Diversity and Inclusion": "N/A", "Career Opportunities": 3, "Compensation and Benefits": 1, "Senior Management": 3, "review_title": "A nice place to work with great colleagues", "rating": "4.0", "reviewer_affiliation": "Current Employee, more than 8 years", "job_date": "8 Mar 2020", "job_title": "Associate Professor in Bloomington, IL", "duration": "N/A", "pros": "motivated students, opportunities for interdisciplinary work", "cons": "low salary and high workload"}, {"Recommended": "Yes", "CEO Approval": "N/A", "Business Outlook": "Neutral", "Work/Life Balance": 0, "Culture & Values": 3, "Diversity and Inclusion": "N/A", "Career Opportunities": 0, "Compensation and Benefits": 1, "Senior Management": 4, "review_title": "Financial Aid", "rating": "2.0", "reviewer_affiliation": "Current Employee, more than 1 year", "job_date": "26 Apr 2017", "job_title": "Financial Aid Coordinator in Bloomington, IL", "duration": "N/A", "pros": "Work with a great team", "cons": "No promotions or raise in pay"}, {"Recommended": "Yes", "CEO Approval": "Yes", "Business Outlook": "Good", "Work/Life Balance": 5, "Culture & Values": 5, "Diversity and Inclusion": "N/A", "Career Opportunities": 3, "Compensation and Benefits": 3, "Senior Management": 3, "review_title": "Great environment, great people", "rating": "5.0", "reviewer_affiliation": "Former Employee, more than 1 year", "job_date": "6 Feb 2014", "job_title": "Desk Aide in Bloomington, IL", "duration": "N/A", "pros": "IWU is great all around", "cons": "Can't think of any cons"}, {"Recommended": "Yes", "CEO Approval": "Neutral", "Business Outlook": "Neutral", "Work/Life Balance": 4, "Culture & Values": 5, "Diversity and Inclusion": "N/A", "Career Opportunities": 4, "Compensation and Benefits": 5, "Senior Management": "N/A", "review_title": "Small, supportive community", "rating": "5.0", "reviewer_affiliation": "Current Employee, more than 1 year", "job_date": "20 Apr 2020", "job_title": "Anonymous Employee in Bloomington, IL", "duration": "N/A", "pros": "Supportive, communicative, open, beautiful, strong theatre program", "cons": "Small, reorganizing, middle of nowhere,"}]]