[[{"Recommended": "Yes", "CEO Approval": "Neutral", "Business Outlook": "Neutral", "Work/Life Balance": 4, "Culture & Values": 4, "Diversity and Inclusion": "N/A", "Career Opportunities": 3, "Compensation and Benefits": 4, "Senior Management": 3, "review_title": "IT", "rating": "4.0", "reviewer_affiliation": "Former Employee", "job_date": "7 Oct 2015", "job_title": "IT Manager in Boston", "duration": "N/A", "pros": "flexiable schedule and good benefits", "cons": "need self discipline to keep up the career development. the management is lax."}]]