[[{"Recommended": "N/A", "CEO Approval": "N/A", "Business Outlook": "N/A", "Work/Life Balance": "N/A", "Culture & Values": "N/A", "Diversity and Inclusion": "N/A", "Career Opportunities": "N/A", "Compensation and Benefits": "N/A", "Senior Management": "N/A", "review_title": "Great place to study", "rating": "5.0", "reviewer_affiliation": "Former Employee", "job_date": "21 Jan 2021", "job_title": "R&D Research Scientist in Toronto, ON", "duration": "N/A", "pros": "It is a very collaborative department", "cons": "There are no significant cons"}], [], []]