[[{"Recommended": "Yes", "CEO Approval": "Yes", "Business Outlook": "Good", "Work/Life Balance": 5, "Culture & Values": 5, "Diversity and Inclusion": 5, "Career Opportunities": 5, "Compensation and Benefits": 5, "Senior Management": 5, "review_title": "Good", "rating": "5.0", "reviewer_affiliation": "Current Employee, more than 5 years", "job_date": "24 Nov 2022", "job_title": "Senior Director in Riyadh", "duration": "N/A", "pros": "best place to work at", "cons": "all thing is teh best at this company"}, {"Recommended": "No", "CEO Approval": "No", "Business Outlook": "Bad", "Work/Life Balance": 1, "Culture & Values": 1, "Diversity and Inclusion": 1, "Career Opportunities": 1, "Compensation and Benefits": 1, "Senior Management": 1, "review_title": "Customer service representative", "rating": "1.0", "reviewer_affiliation": "Current Employee", "job_date": "17 May 2023", "job_title": "Customer Service Representative in Riyadh", "duration": "N/A", "pros": "Not good at all nothing", "cons": "Every thing is very bad"}, {"Recommended": "Yes", "CEO Approval": "Yes", "Business Outlook": "Good", "Work/Life Balance": 1, "Culture & Values": 1, "Diversity and Inclusion": 1, "Career Opportunities": 1, "Compensation and Benefits": 1, "Senior Management": 1, "review_title": "a", "rating": "1.0", "reviewer_affiliation": "Current Employee", "job_date": "1 Jan 2023", "job_title": "Associate Director in Riyadh", "duration": "N/A", "pros": "dood for start job ok", "cons": "management need some upgrad thinking"}, {"Recommended": "Yes", "CEO Approval": "Yes", "Business Outlook": "Good", "Work/Life Balance": 4, "Culture & Values": 4, "Diversity and Inclusion": 3, "Career Opportunities": 4, "Compensation and Benefits": 3, "Senior Management": 3, "review_title": "Good", "rating": "5.0", "reviewer_affiliation": "Current Employee, more than 8 years", "job_date": "12 Jul 2022", "job_title": "Planning Engineer in Riyadh", "duration": "N/A", "pros": "Good learning experience and working is Worth", "cons": "Okey but some time overload working"}, {"Recommended": "N/A", "CEO Approval": "N/A", "Business Outlook": "N/A", "Work/Life Balance": 0, "Culture & Values": 0, "Diversity and Inclusion": "N/A", "Career Opportunities": 0, "Compensation and Benefits": 3, "Senior Management": 1, "review_title": "Poor Management at CCC", "rating": "2.0", "reviewer_affiliation": "Former Employee, more than 5 years", "job_date": "17 Oct 2019", "job_title": "Sustainability Manager in Riyadh", "duration": "N/A", "pros": "The company's upper management has good intentions", "cons": "Cronyism, nepotism, corruption, etc"}, {"Recommended": "N/A", "CEO Approval": "Neutral", "Business Outlook": "Good", "Work/Life Balance": 4, "Culture & Values": 4, "Diversity and Inclusion": "N/A", "Career Opportunities": 4, "Compensation and Benefits": 4, "Senior Management": 4, "review_title": "Good", "rating": "4.0", "reviewer_affiliation": "Current Employee, more than 3 years", "job_date": "28 Feb 2018", "job_title": "General Manager in Riyadh", "duration": "N/A", "pros": "Good Company to Work For", "cons": "Not a Bad Company to Work For"}], [], []][[{"Recommended": "Yes", "CEO Approval": "Yes", "Business Outlook": "Good", "Work/Life Balance": 5, "Culture & Values": 5, "Diversity and Inclusion": 5, "Career Opportunities": 5, "Compensation and Benefits": 5, "Senior Management": 5, "review_title": "Good", "rating": "5.0", "reviewer_affiliation": "Current Employee, more than 5 years", "job_date": "24 Nov 2022", "job_title": "Senior Director in Riyadh", "duration": "N/A", "pros": "best place to work at", "cons": "all thing is teh best at this company"}, {"Recommended": "No", "CEO Approval": "No", "Business Outlook": "Bad", "Work/Life Balance": 1, "Culture & Values": 1, "Diversity and Inclusion": 1, "Career Opportunities": 1, "Compensation and Benefits": 1, "Senior Management": 1, "review_title": "Customer service representative", "rating": "1.0", "reviewer_affiliation": "Current Employee", "job_date": "17 May 2023", "job_title": "Customer Service Representative in Riyadh", "duration": "N/A", "pros": "Not good at all nothing", "cons": "Every thing is very bad"}, {"Recommended": "Yes", "CEO Approval": "Yes", "Business Outlook": "Good", "Work/Life Balance": 1, "Culture & Values": 1, "Diversity and Inclusion": 1, "Career Opportunities": 1, "Compensation and Benefits": 1, "Senior Management": 1, "review_title": "a", "rating": "1.0", "reviewer_affiliation": "Current Employee", "job_date": "1 Jan 2023", "job_title": "Associate Director in Riyadh", "duration": "N/A", "pros": "dood for start job ok", "cons": "management need some upgrad thinking"}, {"Recommended": "Yes", "CEO Approval": "Yes", "Business Outlook": "Good", "Work/Life Balance": 4, "Culture & Values": 4, "Diversity and Inclusion": 3, "Career Opportunities": 4, "Compensation and Benefits": 3, "Senior Management": 3, "review_title": "Good", "rating": "5.0", "reviewer_affiliation": "Current Employee, more than 8 years", "job_date": "12 Jul 2022", "job_title": "Planning Engineer in Riyadh", "duration": "N/A", "pros": "Good learning experience and working is Worth", "cons": "Okey but some time overload working"}, {"Recommended": "N/A", "CEO Approval": "N/A", "Business Outlook": "N/A", "Work/Life Balance": 0, "Culture & Values": 0, "Diversity and Inclusion": "N/A", "Career Opportunities": 0, "Compensation and Benefits": 3, "Senior Management": 1, "review_title": "Poor Management at CCC", "rating": "2.0", "reviewer_affiliation": "Former Employee, more than 5 years", "job_date": "17 Oct 2019", "job_title": "Sustainability Manager in Riyadh", "duration": "N/A", "pros": "The company's upper management has good intentions", "cons": "Cronyism, nepotism, corruption, etc"}, {"Recommended": "N/A", "CEO Approval": "Neutral", "Business Outlook": "Good", "Work/Life Balance": 4, "Culture & Values": 4, "Diversity and Inclusion": "N/A", "Career Opportunities": 4, "Compensation and Benefits": 4, "Senior Management": 4, "review_title": "Good", "rating": "4.0", "reviewer_affiliation": "Current Employee, more than 3 years", "job_date": "28 Feb 2018", "job_title": "General Manager in Riyadh", "duration": "N/A", "pros": "Good Company to Work For", "cons": "Not a Bad Company to Work For"}], [], []]