[[{"Recommended": "Yes", "CEO Approval": "N/A", "Business Outlook": "Good", "Work/Life Balance": 5, "Culture & Values": 5, "Diversity and Inclusion": 5, "Career Opportunities": 5, "Compensation and Benefits": 4, "Senior Management": 5, "review_title": "Positive workplace", "rating": "5.0", "reviewer_affiliation": "Current Employee", "job_date": "26 Jul 2021", "job_title": "Speech Language Pathologist in Reseda, CA", "duration": "N/A", "pros": "Great training, positive environment, work as a team.", "cons": "Salary could always be more."}, {"Recommended": "N/A", "CEO Approval": "N/A", "Business Outlook": "N/A", "Work/Life Balance": 5, "Culture & Values": 5, "Diversity and Inclusion": 5, "Career Opportunities": 3, "Compensation and Benefits": 4, "Senior Management": 5, "review_title": "Flexible job", "rating": "4.0", "reviewer_affiliation": "Current Employee, more than 3 years", "job_date": "14 May 2022", "job_title": "Behavior Interventionist in Los Angeles, CA", "duration": "N/A", "pros": "Flexible hours, Good supervisors, Feel valued", "cons": "Low pay, not many raises"}, {"Recommended": "Yes", "CEO Approval": "N/A", "Business Outlook": "Good", "Work/Life Balance": 3, "Culture & Values": 3, "Diversity and Inclusion": "N/A", "Career Opportunities": 3, "Compensation and Benefits": 3, "Senior Management": 4, "review_title": "Teacher Assistant", "rating": "5.0", "reviewer_affiliation": "Former Employee, more than 1 year", "job_date": "30 Oct 2016", "job_title": "Teacher Assistant in Newark, NJ", "duration": "N/A", "pros": "I am good with my administrators very helpful in instructing", "cons": "they were only there as an interim agency"}, {"Recommended": "Yes", "CEO Approval": "N/A", "Business Outlook": "Good", "Work/Life Balance": 5, "Culture & Values": 5, "Diversity and Inclusion": "N/A", "Career Opportunities": 5, "Compensation and Benefits": 5, "Senior Management": 5, "review_title": "Behavioral Therapist", "rating": "5.0", "reviewer_affiliation": "Current Employee, more than 1 year", "job_date": "13 Nov 2017", "job_title": "Behavioral Interventionist in Woodland Hills, CA", "duration": "N/A", "pros": "Endless support and team work\r\nLearned many professional developments and skills\r\nBenefits\r\nReally cares about their employees", "cons": "Pay is not enough\r\nStressful\r\nBase Salary; no raises"}, {"Recommended": "Yes", "CEO Approval": "N/A", "Business Outlook": "Neutral", "Work/Life Balance": 4, "Culture & Values": 5, "Diversity and Inclusion": "N/A", "Career Opportunities": 0, "Compensation and Benefits": 3, "Senior Management": 4, "review_title": "Good for internship", "rating": "4.0", "reviewer_affiliation": "Current Intern, more than 3 years", "job_date": "25 Apr 2017", "job_title": "Marriage and Family Therapy in Woodland Hills, CA", "duration": "N/A", "pros": "supervision, client load, will get hours quickly, paid", "cons": "no room for growth, admin always changing, no pay increase, not always informing about benefits"}], []]