[[{"Recommended": "Yes", "CEO Approval": "Yes", "Business Outlook": "Good", "Work/Life Balance": 5, "Culture & Values": 4, "Diversity and Inclusion": 4, "Career Opportunities": 5, "Compensation and Benefits": 5, "Senior Management": 4, "review_title": "Excellent place to work", "rating": "5.0", "reviewer_affiliation": "Current Employee, more than 5 years", "job_date": "19 Oct 2021", "job_title": "Engagement Specialist in Melbourne, AR", "duration": "N/A", "pros": "Great support and modern systems\nDiverse\nFriendly", "cons": "Office politics can be an issue."}, {"Recommended": "N/A", "CEO Approval": "N/A", "Business Outlook": "N/A", "Work/Life Balance": "N/A", "Culture & Values": "N/A", "Diversity and Inclusion": "N/A", "Career Opportunities": "N/A", "Compensation and Benefits": "N/A", "Senior Management": "N/A", "review_title": "1", "rating": "4.0", "reviewer_affiliation": "Current Employee", "job_date": "4 Jan 2023", "job_title": "Research Assistant II in Bangor, ME", "duration": "N/A", "pros": "Worth working very good opportunity", "cons": "I don't have any shortcomings. I like it very much."}, {"Recommended": "N/A", "CEO Approval": "N/A", "Business Outlook": "N/A", "Work/Life Balance": "N/A", "Culture & Values": "N/A", "Diversity and Inclusion": "N/A", "Career Opportunities": "N/A", "Compensation and Benefits": "N/A", "Senior Management": "N/A", "review_title": "HR Advisor", "rating": "3.0", "reviewer_affiliation": "Former Employee, less than 1 year", "job_date": "28 Feb 2022", "job_title": "Human Resources Advisor in Melbourne, FL", "duration": "N/A", "pros": "Additional super and good starting base salary", "cons": "High volume of workload completed on the phones like a call center"}, {"Recommended": "Yes", "CEO Approval": "Neutral", "Business Outlook": "Neutral", "Work/Life Balance": 5, "Culture & Values": 4, "Diversity and Inclusion": "N/A", "Career Opportunities": 3, "Compensation and Benefits": 4, "Senior Management": 4, "review_title": "Nice and relaxed environment", "rating": "4.0", "reviewer_affiliation": "Former Employee, less than 1 year", "job_date": "18 Dec 2016", "job_title": " in Cary, NC", "duration": "N/A", "pros": "You can do so many things in the Campus Centre. They have banks, post office, travel agents, etc.\r\nPeople in the climate group were very friendly.", "cons": "Salary could be better. Usually when they publish jobs they write the number including superannuation, so your actual pay is less that what it looks at first glance."}, {"Recommended": "Yes", "CEO Approval": "N/A", "Business Outlook": "Good", "Work/Life Balance": 4, "Culture & Values": 4, "Diversity and Inclusion": "N/A", "Career Opportunities": 4, "Compensation and Benefits": 4, "Senior Management": 3, "review_title": "monash", "rating": "4.0", "reviewer_affiliation": "Current Employee", "job_date": "11 Oct 2016", "job_title": "Research Officer in Clayton, OH", "duration": "N/A", "pros": "Fair, huge employer, good people", "cons": "Lot short term contracts given"}], [], [], [], [], []]