[[{"Recommended": "Yes", "CEO Approval": "Yes", "Business Outlook": "Good", "Work/Life Balance": 5, "Culture & Values": 5, "Diversity and Inclusion": 5, "Career Opportunities": 5, "Compensation and Benefits": 5, "Senior Management": 5, "review_title": "Good", "rating": "5.0", "reviewer_affiliation": "Former Employee", "job_date": "21 Feb 2021", "job_title": "Registered Nurse, BSN in Edmonton, AB", "duration": "N/A", "pros": "Good place to work as a health care worker.", "cons": "None. No cons that I can remember."}, {"Recommended": "Yes", "CEO Approval": "Neutral", "Business Outlook": "Neutral", "Work/Life Balance": 3, "Culture & Values": 3, "Diversity and Inclusion": 3, "Career Opportunities": 3, "Compensation and Benefits": 3, "Senior Management": 3, "review_title": "Registered Critical Care Nurse", "rating": "3.0", "reviewer_affiliation": "Current Employee", "job_date": "17 Jan 2021", "job_title": "Registered Nurse in Edmonton, AB", "duration": "N/A", "pros": "A kind caring compassionate company", "cons": "fairly younger management with bad follow-ups"}], []]