[[{"Recommended": "N/A", "CEO Approval": "N/A", "Business Outlook": "N/A", "Work/Life Balance": "N/A", "Culture & Values": 4, "Diversity and Inclusion": 4, "Career Opportunities": 4, "Compensation and Benefits": 4, "Senior Management": "N/A", "review_title": "Good", "rating": "4.0", "reviewer_affiliation": "Current Employee, less than 1 year", "job_date": "2 Apr 2023", "job_title": "Registered Nurse in London, England", "duration": "N/A", "pros": "Healthy, good I love it", "cons": "None that I know of"}, {"Recommended": "Yes", "CEO Approval": "N/A", "Business Outlook": "Good", "Work/Life Balance": 0, "Culture & Values": 4, "Diversity and Inclusion": 4, "Career Opportunities": 3, "Compensation and Benefits": 0, "Senior Management": 4, "review_title": "Good organisation", "rating": "4.0", "reviewer_affiliation": "Current Employee", "job_date": "28 Aug 2021", "job_title": "Medical Doctor in Birmingham, England", "duration": "N/A", "pros": "stable, well respected and good environment to develop", "cons": "Busy most of the time"}], [], []]