[[{"Recommended": "Yes", "CEO Approval": "Yes", "Business Outlook": "Good", "Work/Life Balance": 5, "Culture & Values": 5, "Diversity and Inclusion": 5, "Career Opportunities": 5, "Compensation and Benefits": 5, "Senior Management": 4, "review_title": "A very formal environment, no clutter management", "rating": "5.0", "reviewer_affiliation": "Former Employee, more than 1 year", "job_date": "11 May 2023", "job_title": "Sanitation Business Advisor in Khulna", "duration": "N/A", "pros": "- SNV is a global organisation, you'll get a lot to learn there. - SNV respects employee privacy and security. - The safeguarding policy is one of the best in Bangladesh. - Working with WASH sector colleagues kept myself in a very friendly environment. - Never undervalue its staffs.", "cons": "- You'll get less networking opportunity if you work at field. - Learning curve is a bit slow comparing with other WASH organisations in Bangladesh, but learning opportunities are there."}, {"Recommended": "Yes", "CEO Approval": "Yes", "Business Outlook": "Good", "Work/Life Balance": 3, "Culture & Values": 4, "Diversity and Inclusion": 0, "Career Opportunities": 0, "Compensation and Benefits": 3, "Senior Management": 4, "review_title": "Good workplace", "rating": "5.0", "reviewer_affiliation": "Former Employee, more than 1 year", "job_date": "22 Apr 2023", "job_title": "Communication Officer in Dhaka", "duration": "N/A", "pros": "Helps me learn a lot and grow", "cons": "Management of project could be done better"}, {"Recommended": "Yes", "CEO Approval": "Yes", "Business Outlook": "Bad", "Work/Life Balance": 4, "Culture & Values": 4, "Diversity and Inclusion": "N/A", "Career Opportunities": 3, "Compensation and Benefits": 3, "Senior Management": 5, "review_title": "Sustainability of Organization in Bangladesh", "rating": "4.0", "reviewer_affiliation": "Current Employee, less than 1 year", "job_date": "7 Nov 2019", "job_title": "Communication and Knowledge Management Advisor in Dhaka", "duration": "N/A", "pros": "Flexible working environment, freedom of working, moderate pay", "cons": "No feasible business development plan to sustain. Poor branding and visibility. Detached from social media."}], []]