[[{"Recommended": "N/A", "CEO Approval": "N/A", "Business Outlook": "N/A", "Work/Life Balance": "N/A", "Culture & Values": "N/A", "Diversity and Inclusion": "N/A", "Career Opportunities": "N/A", "Compensation and Benefits": "N/A", "Senior Management": "N/A", "review_title": "Great !", "rating": "5.0", "reviewer_affiliation": "Former Employee", "job_date": "21 Dec 2022", "job_title": "Exercise Therapist in Boston, MA", "duration": "N/A", "pros": "Flexible hours Can work in the various locations On job training", "cons": "May require additional training and or certifications"}, {"Recommended": "Yes", "CEO Approval": "N/A", "Business Outlook": "Good", "Work/Life Balance": 4, "Culture & Values": 4, "Diversity and Inclusion": 4, "Career Opportunities": 4, "Compensation and Benefits": 4, "Senior Management": 4, "review_title": "Great environment", "rating": "4.0", "reviewer_affiliation": "Current Employee, less than 1 year", "job_date": "3 Apr 2023", "job_title": "Anonymous Employee in Boston, MA", "duration": "N/A", "pros": "Work life balance Benefits Time off", "cons": "Training is lacking for new employees"}, {"Recommended": "N/A", "CEO Approval": "N/A", "Business Outlook": "N/A", "Work/Life Balance": 5, "Culture & Values": 5, "Diversity and Inclusion": 5, "Career Opportunities": 5, "Compensation and Benefits": 5, "Senior Management": 5, "review_title": "Great Place To Work", "rating": "5.0", "reviewer_affiliation": "Current Employee, more than 1 year", "job_date": "11 Nov 2021", "job_title": "Physical Therapist in Roslindale, MA", "duration": "N/A", "pros": "Great coworkers, great management, flexible scheduling", "cons": "None that I can think of"}, {"Recommended": "Yes", "CEO Approval": "N/A", "Business Outlook": "Good", "Work/Life Balance": 4, "Culture & Values": 4, "Diversity and Inclusion": "N/A", "Career Opportunities": 5, "Compensation and Benefits": 4, "Senior Management": 3, "review_title": "Welcoming", "rating": "4.0", "reviewer_affiliation": "Former Employee, more than 3 years", "job_date": "6 Dec 2015", "job_title": "Utility and Tray Line Service Associate in Brockton, MA", "duration": "N/A", "pros": "Flexible school schedule \r\nFamily like environment \r\nAlways moving forward", "cons": "I left to seek other opportunities. I was a new grad and it was time to leave my college part time. it was a very stressful environment because of the new changes but great company to work for"}, {"Recommended": "Yes", "CEO Approval": "N/A", "Business Outlook": "N/A", "Work/Life Balance": "N/A", "Culture & Values": "N/A", "Diversity and Inclusion": "N/A", "Career Opportunities": "N/A", "Compensation and Benefits": "N/A", "Senior Management": 4, "review_title": "PRN COTA", "rating": "4.0", "reviewer_affiliation": "Former Employee, more than 3 years", "job_date": "27 Nov 2015", "job_title": " in North Miami, FL", "duration": "N/A", "pros": "Good rehab team, very helpful,  nursing staff was very good as well", "cons": "Documentation system had some glitches, was difficult to find IT support, especially on the weekends"}, {"Recommended": "Yes", "CEO Approval": "N/A", "Business Outlook": "Good", "Work/Life Balance": 4, "Culture & Values": 4, "Diversity and Inclusion": "N/A", "Career Opportunities": 4, "Compensation and Benefits": 4, "Senior Management": 4, "review_title": "Great Place to work", "rating": "5.0", "reviewer_affiliation": "Former Employee, more than 10 years", "job_date": "30 Jun 2016", "job_title": "Charge/Staff Nurse in Wareham, MA", "duration": "N/A", "pros": "Good retirement package, very loyal to the employees.", "cons": "Don't have a big per diem pool so if someone calls out you stay for another shift."}, {"Recommended": "Yes", "CEO Approval": "N/A", "Business Outlook": "Good", "Work/Life Balance": 3, "Culture & Values": 5, "Diversity and Inclusion": "N/A", "Career Opportunities": 5, "Compensation and Benefits": 3, "Senior Management": 3, "review_title": "LPN", "rating": "5.0", "reviewer_affiliation": "Former Employee, more than 5 years", "job_date": "22 Jul 2015", "job_title": "Practical Nurse in Boston, MA", "duration": "N/A", "pros": "Wonderful team atmosphere\r\n\r\nGreat work ethic\r\n\r\nRecent programs to uplift and appreciate workers", "cons": "HR can be disorganized at times"}, {"Recommended": "No", "CEO Approval": "N/A", "Business Outlook": "Bad", "Work/Life Balance": 0, "Culture & Values": 1, "Diversity and Inclusion": "N/A", "Career Opportunities": 1, "Compensation and Benefits": 3, "Senior Management": 1, "review_title": "Sr Payroll Coordinator", "rating": "1.0", "reviewer_affiliation": "Former Employee, more than 1 year", "job_date": "29 Dec 2015", "job_title": "Senior Payroll Coordinator in Boston, MA", "duration": "N/A", "pros": "Competitive Salary, Decent  Benefits Plan", "cons": "Archaic and Antiquated Practices and Systems. A general resistance to better any process if it means anyone will be uncomfortable with the change."}, {"Recommended": "Yes", "CEO Approval": "N/A", "Business Outlook": "Good", "Work/Life Balance": 3, "Culture & Values": 4, "Diversity and Inclusion": "N/A", "Career Opportunities": 3, "Compensation and Benefits": 3, "Senior Management": 3, "review_title": "GREAT PLACE", "rating": "4.0", "reviewer_affiliation": "Former Employee", "job_date": "16 Oct 2016", "job_title": "CNA in Boston, MA", "duration": "N/A", "pros": "Friendly environment and great  place to work and learn.", "cons": "No benefits for part timers"}, {"Recommended": "Yes", "CEO Approval": "N/A", "Business Outlook": "Good", "Work/Life Balance": 5, "Culture & Values": 4, "Diversity and Inclusion": "N/A", "Career Opportunities": 0, "Compensation and Benefits": 3, "Senior Management": 3, "review_title": "Analyst-IT", "rating": "4.0", "reviewer_affiliation": "Former Employee, more than 5 years", "job_date": "26 Oct 2015", "job_title": " in Boston, MA", "duration": "N/A", "pros": "Wonderful coworkers, free-parking, flexible schedule", "cons": "Few new projects, no upward career mobility"}], []]